{
    "header": {
        "title": "Cho Thuê Mặt Bằng, Giá Rẻ, Chính Chủ, Mới Nhất 2024",
        "description": "Cho thuê mặt bằng: giá rẻ, chính chủ, gần chợ, trường học, tiện mở quán ăn, cafe, kinh doanh mọi ngành nghề. Đăng tin cho thuê mặt bằng hiệu quả tại Phongtro123.com"
    },
    "body": [
        {
            "images": [
                "https://pt123.cdn.static123.com/images/thumbs/900x600/fit/2024/05/18/17101716-927073107395829-1088053046-n_1715979046.jpg",
                "https://pt123.cdn.static123.com/images/thumbs/900x600/fit/2024/05/18/50853954-219321752350543-2869661185978925056-n_1715979033.jpg",
                "https://pt123.cdn.static123.com/images/thumbs/900x600/fit/2024/05/18/20201102104247-5e41-wm_1715979033.jpg",
                "https://pt123.cdn.static123.com/images/thumbs/900x600/fit/2024/05/18/17101716-927073107395829-1088053046-n_1715979046.jpg",
                "https://pt123.cdn.static123.com/images/thumbs/900x600/fit/2024/05/18/50853954-219321752350543-2869661185978925056-n_1715979033.jpg"
            ],
            "header": {
                "title": "Văn Phòng cho thuê HXH 21 Trường Sơn, P.4, Q.Tân Bình (Ngay sân bay TSN)",
                "address": "Địa chỉ: 21/1 Trường Sơn, Phường 4, Quận Tân Bình, Hồ Chí Minh",
                "attributes": {
                    "price": "4.8 triệu/tháng",
                    "acreage": "30m2",
                    "published": "2 giờ trước",
                    "hashtag": "655080"
                }
            },
            "mainContent": {
                "header": "Thông tin mô tả",
                "content": [
                    "Cho thuê văn phòng ngay tầng trệt nhà hẻm xe hơi 6m 21/1 Trường Sơn, P.4, Q.Tân Bình – Ngay đường ra sân bay, kế bên khu văn phòng nhiều đường lớn ra vào thuận tiện, tiện ngay khu văn phòng hoặc các kho hàng gần sân bay. (đường Thăng Long, Ba Vì, Hoàng Văn Thụ …)",
                    "– Thiết kế với lối đi riêng biệt rất đẹp, tiện mở văn phòng làm việc hoặc làm kho để đồ.",
                    "+ Diện Tích cụ thể: 4.5 m x 7m",
                    "+ Văn Phòng đã được thiết kế sẵn với cửa kính, tường ngăn riêng biệt, WC riêng, cửa sổ thoáng mát, có thể làm văn phòng, kho lưu trữ đồ trưng bày sản phẩm hoặc ở lại.",
                    "+ Nhà Mặt Tiền hẻm xe 2 xe hơi tránh nhau gần sát sân bay, khu dân cư an ninh, yên tĩnh",
                    "+ Nhà có chỗ để xe rộng rãi với camera an ninh 24/24 rất an toàn.",
                    "+ Khoá vân tay, giờ giấc tự do cho bạn cảm giác như ở chính nhà mình.",
                    "+ Vị trí thuận lợi: Ngay ngã ba Hậu Giang – Trường Sơn, Ngay cùng phía đường ra sân bay (có thể đi bộ được), gần ngã ba công viên Hoàng Văn Thụ, tiện đi lại mọi nơi trong thành phố.",
                    "+ Giá rất hợp lý giảm sâu chỉ: 4.8 Triệu/tháng.",
                    "+ LH: 0937554570 (A.Hoàng) – Địa chỉ: 21/1 Trường Sơn, P.4, Q.Tân Bình",
                    "Từ Khoá: cho thuê văn phòng hcm, văn phòng cho thuê quận Tân Bình.",
                    "Cho thuê kho hcm, cho thuê kho quận tân bình gần sân bay."
                ]
            },
            "overview": {
                "header": "Đặc điểm tin đăng",
                "content": [
                    {
                        "name": "Mã tin:",
                        "content": "#655080"
                    },
                    {
                        "name": "Chuyên mục:",
                        "content": "Cho thuê mặt bằng Quận Tân Bình"
                    },
                    {
                        "name": "Khu vực",
                        "content": "Cho thuê mặt bằng Hồ Chí Minh"
                    },
                    {
                        "name": "Loại tin rao:",
                        "content": "Cho thuê mặt bằng"
                    },
                    {
                        "name": "Đối tượng thuê:",
                        "content": "Tất cả"
                    },
                    {
                        "name": "Gói tin:",
                        "content": "Tin thường"
                    },
                    {
                        "name": "Ngày đăng:",
                        "content": "Thứ 3, 18:25 09/07/2024"
                    },
                    {
                        "name": "Ngày hết hạn:",
                        "content": "Thứ 5, 11:22 11/07/2024"
                    }
                ]
            },
            "contact": {
                "header": "Thông tin liên hệ",
                "content": [
                    {
                        "name": "Liên hệ:",
                        "content": "hoangle2706"
                    },
                    {
                        "name": "Điện thoại:",
                        "content": "0937554570"
                    },
                    {
                        "name": "Zalo",
                        "content": "0937554570"
                    }
                ]
            }
        },
        {
            "images": [
                "https://pt123.cdn.static123.com/images/thumbs/900x600/fit/2024/07/09/img-7918_1720523105.jpg",
                "https://pt123.cdn.static123.com/images/thumbs/900x600/fit/2024/07/09/img-7926_1720523101.jpg",
                "https://pt123.cdn.static123.com/images/thumbs/900x600/fit/2024/07/09/img-7925_1720523101.jpg",
                "https://pt123.cdn.static123.com/images/thumbs/900x600/fit/2024/07/09/img-7924_1720523102.jpg",
                "https://pt123.cdn.static123.com/images/thumbs/900x600/fit/2024/07/09/img-7923_1720523103.jpg",
                "https://pt123.cdn.static123.com/images/thumbs/900x600/fit/2024/07/09/img-7922_1720523103.jpg",
                "https://pt123.cdn.static123.com/images/thumbs/900x600/fit/2024/07/09/img-7921_1720523104.jpg",
                "https://pt123.cdn.static123.com/images/thumbs/900x600/fit/2024/07/09/img-7920_1720523104.jpg",
                "https://pt123.cdn.static123.com/images/thumbs/900x600/fit/2024/07/09/img-7919_1720523105.jpg",
                "https://pt123.cdn.static123.com/images/thumbs/900x600/fit/2024/07/09/img-7918_1720523105.jpg",
                "https://pt123.cdn.static123.com/images/thumbs/900x600/fit/2024/07/09/img-7926_1720523101.jpg"
            ],
            "header": {
                "title": "Cần thanh lý Mặt bằng gấp, 149/B15 Lý Thánh Tông, Tân Thới Hòa, Tân PhúGiá chỉ 5trieu/tháng",
                "address": "Địa chỉ: 149/B15 Đường Lý Thánh Tông, Phường Tân Thới Hòa, Quận Tân Phú, Hồ Chí Minh",
                "attributes": {
                    "price": "5 triệu/tháng",
                    "acreage": "16m2",
                    "published": "3 giờ trước",
                    "hashtag": "659503"
                }
            },
            "mainContent": {
                "header": "Thông tin mô tả",
                "content": [
                    "Do nhu cầu chuyển về mặt bằng khác kinh doanh, em cần thanh lý mặt bằng đang thuê gấp.",
                    "149/B15 Lý Thánh Tông, Tân Thới Hòa, Tân Phú",
                    "Giá chỉ 5trieu/tháng, cọc 2 tháng,",
                    "-dọn vào kinh doanh luôn, phù hợp cho spa, quán cơm, ăn uống,…(xung quanh có công ty xí nghiệp nhỏ)",
                    "- gần chợ",
                    "-gần trường THCS Tân Thới Hoà",
                    "-có chỗ để xe,",
                    "Đường 7m"
                ]
            },
            "overview": {
                "header": "Đặc điểm tin đăng",
                "content": [
                    {
                        "name": "Mã tin:",
                        "content": "#659503"
                    },
                    {
                        "name": "Chuyên mục:",
                        "content": "Cho thuê mặt bằng Quận Tân Phú"
                    },
                    {
                        "name": "Khu vực",
                        "content": "Cho thuê mặt bằng Hồ Chí Minh"
                    },
                    {
                        "name": "Loại tin rao:",
                        "content": "Cho thuê mặt bằng"
                    },
                    {
                        "name": "Đối tượng thuê:",
                        "content": "Tất cả"
                    },
                    {
                        "name": "Gói tin:",
                        "content": "Tin miễn phí"
                    },
                    {
                        "name": "Ngày đăng:",
                        "content": "Thứ 3, 18:05 09/07/2024"
                    },
                    {
                        "name": "Ngày hết hạn:",
                        "content": "Chủ Nhật, 18:05 14/07/2024"
                    }
                ]
            },
            "contact": {
                "header": "Thông tin liên hệ",
                "content": [
                    {
                        "name": "Liên hệ:",
                        "content": "Ngọc Chăm"
                    },
                    {
                        "name": "Điện thoại:",
                        "content": "0327379939"
                    },
                    {
                        "name": "Zalo",
                        "content": "0327379939"
                    }
                ]
            }
        },
        {
            "images": [
                "https://pt123.cdn.static123.com/images/thumbs/900x600/fit/2023/02/09/6_1675931203.jpg",
                "https://pt123.cdn.static123.com/images/thumbs/900x600/fit/2023/02/09/2_1675931202.jpg",
                "https://pt123.cdn.static123.com/images/thumbs/900x600/fit/2023/02/09/6_1675931203.jpg",
                "https://pt123.cdn.static123.com/images/thumbs/900x600/fit/2023/02/09/2_1675931202.jpg"
            ],
            "header": {
                "title": "Cho thuê rẻ mặt bằng 8 x 20m Nguyễn Trãi Bến Thành Q1 trung tâm TP.HCM",
                "address": "Địa chỉ: Nguyễn Trãi, Phường Bến Thành, Quận 1, Hồ Chí Minh",
                "attributes": {
                    "price": "40 triệu/tháng",
                    "acreage": "160m2",
                    "published": "5 giờ trước",
                    "hashtag": "615671"
                }
            },
            "mainContent": {
                "header": "Thông tin mô tả",
                "content": [
                    "- Cần cho thuê rẻ mặt bằng mặt tiền Nguyễn Trãi Phường Bến Thành trung tâm Q1 Thành Phố Sài Gòn, khu trí thức, văn phòng, kinh doanh buôn bán sầm uất.",
                    "- Giao thông thuận tiện, tọa lạc ngay trung tâm thành phố, gần trung tâm thương mại, ngân hàng, siêu thị, khách sạn New World, Chợ Bến Thành…",
                    "- Tiện nghi đầy đủ, DT: 8 x 20m trống suốt, thang máy, tiện mở văn phòng, Spa và các loại hình dịch vụ khác.",
                    "- Giá cho thuê siêu rẻ cho tháng Giêng: 45 tr/ tháng, cọc 3 tháng, thanh toán đầu tháng, hợp đồng dài hạn.",
                    "- Vui lòng liên hệ A Sơn 0817.40.96.96"
                ]
            },
            "overview": {
                "header": "Đặc điểm tin đăng",
                "content": [
                    {
                        "name": "Mã tin:",
                        "content": "#615671"
                    },
                    {
                        "name": "Chuyên mục:",
                        "content": "Cho thuê mặt bằng Quận 1"
                    },
                    {
                        "name": "Khu vực",
                        "content": "Cho thuê mặt bằng Hồ Chí Minh"
                    },
                    {
                        "name": "Loại tin rao:",
                        "content": "Cho thuê mặt bằng"
                    },
                    {
                        "name": "Đối tượng thuê:",
                        "content": "Tất cả"
                    },
                    {
                        "name": "Gói tin:",
                        "content": "Tin thường"
                    },
                    {
                        "name": "Ngày đăng:",
                        "content": "Thứ 3, 15:24 09/07/2024"
                    },
                    {
                        "name": "Ngày hết hạn:",
                        "content": "Thứ 4, 11:12 10/07/2024"
                    }
                ]
            },
            "contact": {
                "header": "Thông tin liên hệ",
                "content": [
                    {
                        "name": "Liên hệ:",
                        "content": "Anh Sơn"
                    },
                    {
                        "name": "Điện thoại:",
                        "content": "0817409696"
                    },
                    {
                        "name": "Zalo",
                        "content": "0817409696"
                    }
                ]
            }
        },
        {
            "images": [
                "https://pt123.cdn.static123.com/images/thumbs/900x600/fit/2024/06/24/9b76440a-c59c-48e2-9c3d-b924ec245719_1719205283.jpg",
                "https://pt123.cdn.static123.com/images/thumbs/900x600/fit/2024/06/24/bbb46053-215f-44ac-9206-18e456c0fe2b_1719205268.jpg",
                "https://pt123.cdn.static123.com/images/thumbs/900x600/fit/2024/06/24/d83cf49e-8944-40bd-bba1-a2ad7e909010_1719205268.jpg",
                "https://pt123.cdn.static123.com/images/thumbs/900x600/fit/2024/06/24/cd29184c-d918-4973-87eb-52c3b293185a_1719205277.jpg",
                "https://pt123.cdn.static123.com/images/thumbs/900x600/fit/2024/06/24/89478aee-5ce0-4a1d-9d8c-ae273e210c2f_1719205277.jpg",
                "https://pt123.cdn.static123.com/images/thumbs/900x600/fit/2024/06/24/057beeea-2885-4ebc-a39e-4d38484afb52_1719205283.jpg",
                "https://pt123.cdn.static123.com/images/thumbs/900x600/fit/2024/06/24/9b76440a-c59c-48e2-9c3d-b924ec245719_1719205283.jpg"
            ],
            "header": {
                "title": "Cho thuê mặt bằng kinh doanh 2 mặt tiền, dt 8x8, đường bàu cát 1",
                "address": "Địa chỉ: 4 Bàu Cát 1, Phường 14, Quận Tân Bình, Hồ Chí Minh",
                "attributes": {
                    "price": "20 triệu/tháng",
                    "acreage": "64m2",
                    "published": "6 giờ trước",
                    "hashtag": "658088"
                }
            },
            "mainContent": {
                "header": "Thông tin mô tả",
                "content": [
                    "Cho thuê mặt bằng kinh doanh 2 mặt tiền",
                    "Dt 8x8 mặt bằng đã hoàn thiện ( sạch đẹp )",
                    "Phù hợp mở văn phòng , showroom trưng bày . Mở tiệm ……",
                    "Giá 20tr",
                    "Liên hệ ngay: 0913190189"
                ]
            },
            "overview": {
                "header": "Đặc điểm tin đăng",
                "content": [
                    {
                        "name": "Mã tin:",
                        "content": "#658088"
                    },
                    {
                        "name": "Chuyên mục:",
                        "content": "Cho thuê mặt bằng Quận Tân Bình"
                    },
                    {
                        "name": "Khu vực",
                        "content": "Cho thuê mặt bằng Hồ Chí Minh"
                    },
                    {
                        "name": "Loại tin rao:",
                        "content": "Cho thuê mặt bằng"
                    },
                    {
                        "name": "Đối tượng thuê:",
                        "content": "Tất cả"
                    },
                    {
                        "name": "Gói tin:",
                        "content": "Tin thường"
                    },
                    {
                        "name": "Ngày đăng:",
                        "content": "Thứ 3, 14:40 09/07/2024"
                    },
                    {
                        "name": "Ngày hết hạn:",
                        "content": "Thứ 4, 09:29 10/07/2024"
                    }
                ]
            },
            "contact": {
                "header": "Thông tin liên hệ",
                "content": [
                    {
                        "name": "Liên hệ:",
                        "content": "Đặng Hiệp"
                    },
                    {
                        "name": "Điện thoại:",
                        "content": "0913190189"
                    },
                    {
                        "name": "Zalo",
                        "content": "0913190189"
                    }
                ]
            }
        },
        {
            "images": [
                "https://pt123.cdn.static123.com/images/thumbs/900x600/fit/2021/01/06/b6bcd216-8aab-4fb8-b641-9834d1b70c42_1609917584.jpg",
                "https://pt123.cdn.static123.com/images/thumbs/900x600/fit/2021/01/06/7e1e8e78-6066-42aa-b6cb-006b48b260a0_1609917585.jpg",
                "https://pt123.cdn.static123.com/images/thumbs/900x600/fit/2021/01/06/63cc24c7-f59b-448e-b003-bfcbf00cc583_1609917584.jpg",
                "https://pt123.cdn.static123.com/images/thumbs/900x600/fit/2021/01/06/077119eb-0ba5-488c-8482-76ca1b41ce11_1609917585.jpg",
                "https://pt123.cdn.static123.com/images/thumbs/900x600/fit/2021/01/06/b6bcd216-8aab-4fb8-b641-9834d1b70c42_1609917584.jpg",
                "https://pt123.cdn.static123.com/images/thumbs/900x600/fit/2021/01/06/7e1e8e78-6066-42aa-b6cb-006b48b260a0_1609917585.jpg"
            ],
            "header": {
                "title": "Mặt bằng 3,0 triệu/ tháng gần chợ Lạc Quan Khu dân cư đông đúc",
                "address": "Địa chỉ: 11/8 Đường Tân Thới Nhất 12, Phường Tân Thới Nhất, Quận 12, Hồ Chí Minh",
                "attributes": {
                    "price": "3 triệu/tháng",
                    "acreage": "20m2",
                    "published": "7 giờ trước",
                    "hashtag": "317373"
                }
            },
            "mainContent": {
                "header": "Thông tin mô tả",
                "content": [
                    "Mặt bằng đường lớn gần chợ Lạc Quan, nhà may Phương Đông, 20m2, dân cư đông đúc, phía sau có khu phòng trọ.",
                    "- Có gác, vệ sinh, kệ bếp, có chỗ ở.",
                    "- Điện 3,5k, nước máy( công ty) 80k/ người",
                    "Cây xăng Phan Văn Hớn chạy thẳng vào thẳng vào."
                ]
            },
            "overview": {
                "header": "Đặc điểm tin đăng",
                "content": [
                    {
                        "name": "Mã tin:",
                        "content": "#317373"
                    },
                    {
                        "name": "Chuyên mục:",
                        "content": "Cho thuê mặt bằng Quận 12"
                    },
                    {
                        "name": "Khu vực",
                        "content": "Cho thuê mặt bằng Hồ Chí Minh"
                    },
                    {
                        "name": "Loại tin rao:",
                        "content": "Cho thuê mặt bằng"
                    },
                    {
                        "name": "Đối tượng thuê:",
                        "content": "Tất cả"
                    },
                    {
                        "name": "Gói tin:",
                        "content": "Tin thường"
                    },
                    {
                        "name": "Ngày đăng:",
                        "content": "Thứ 3, 13:33 09/07/2024"
                    },
                    {
                        "name": "Ngày hết hạn:",
                        "content": "Thứ 6, 15:07 12/07/2024"
                    }
                ]
            },
            "contact": {
                "header": "Thông tin liên hệ",
                "content": [
                    {
                        "name": "Liên hệ:",
                        "content": "Hoang van dong"
                    },
                    {
                        "name": "Điện thoại:",
                        "content": "0984656184"
                    },
                    {
                        "name": "Zalo",
                        "content": "0984656184"
                    }
                ]
            }
        },
        {
            "images": [
                "https://pt123.cdn.static123.com/images/thumbs/900x600/fit/2024/06/25/443710840-10168939359645191-8158106893692483627-n-1_1719306686.jpg",
                "https://pt123.cdn.static123.com/images/thumbs/900x600/fit/2024/06/25/z5549878821240-ff839dd26c9674bbf5d7f18b4e3e6151_1719306594.jpg",
                "https://pt123.cdn.static123.com/images/thumbs/900x600/fit/2024/06/25/366583688-200048596393592-519073266295190060-n_1719306668.jpg",
                "https://pt123.cdn.static123.com/images/thumbs/900x600/fit/2024/06/25/photo-2024-04-12-09-42-25_1719306673.jpg",
                "https://pt123.cdn.static123.com/images/thumbs/900x600/fit/2024/06/25/photo-2023-11-17-10-57-25_1719306678.jpg",
                "https://pt123.cdn.static123.com/images/thumbs/900x600/fit/2024/06/25/443710840-10168939359645191-8158106893692483627-n-1_1719306686.jpg",
                "https://pt123.cdn.static123.com/images/thumbs/900x600/fit/2024/06/25/z5549878821240-ff839dd26c9674bbf5d7f18b4e3e6151_1719306594.jpg"
            ],
            "header": {
                "title": "CHO THUÊ VĂN PHÒNG NGAY TRUNG TÂM QUẬN 10",
                "address": "Địa chỉ: 776/1 Sư Vạn Hạnh, Phường 12, Quận 10, Hồ Chí Minh",
                "attributes": {
                    "price": "90 triệu/tháng",
                    "acreage": "200m2",
                    "published": "11 giờ trước",
                    "hashtag": "658213"
                }
            },
            "mainContent": {
                "header": "Thông tin mô tả",
                "content": [
                    "Tên văn phòng: QUANTUM WORKING SPACE",
                    "Địa chỉ: 766/1 sư vạn hạnh p12 q10",
                    "Kết cấu: 1 tầng",
                    "Diện tích cho thuê: 200m2",
                    "Ngăn sẵn 4 phòng, diện tích phòng meeting nhỏ 15m2, phòng meeting lớn 20m2, phòng master 25m2, boothcall 3m2",
                    "Giá cho thuê: 90 triệu/tháng",
                    "Phí quản lý: $2/m2/tháng",
                    "Phí gửi xe máy: 5k/lượt/ Theo tháng 200k",
                    "Hầm xe sức chứa 50 xe",
                    "Phí ô tô: FREE",
                    "Phí ngoài giờ: Thỏa thuận",
                    "Đặt cọc: 3 tháng",
                    "Thanh toán: Thỏa thuận",
                    "Thời gian thuê: Thỏa thuận"
                ]
            },
            "overview": {
                "header": "Đặc điểm tin đăng",
                "content": [
                    {
                        "name": "Mã tin:",
                        "content": "#658213"
                    },
                    {
                        "name": "Chuyên mục:",
                        "content": "Cho thuê mặt bằng Quận 10"
                    },
                    {
                        "name": "Khu vực",
                        "content": "Cho thuê mặt bằng Hồ Chí Minh"
                    },
                    {
                        "name": "Loại tin rao:",
                        "content": "Cho thuê mặt bằng"
                    },
                    {
                        "name": "Đối tượng thuê:",
                        "content": "Tất cả"
                    },
                    {
                        "name": "Gói tin:",
                        "content": "Tin miễn phí"
                    },
                    {
                        "name": "Ngày đăng:",
                        "content": "Thứ 3, 10:05 09/07/2024"
                    },
                    {
                        "name": "Ngày hết hạn:",
                        "content": "Chủ Nhật, 10:05 14/07/2024"
                    }
                ]
            },
            "contact": {
                "header": "Thông tin liên hệ",
                "content": [
                    {
                        "name": "Liên hệ:",
                        "content": "Tú Mai"
                    },
                    {
                        "name": "Điện thoại:",
                        "content": "0812260762"
                    },
                    {
                        "name": "Zalo",
                        "content": "0812260762"
                    }
                ]
            }
        },
        {
            "images": [
                "https://pt123.cdn.static123.com/images/thumbs/900x600/fit/2024/07/09/20231017164822-e942-wm_1720493626.jpg",
                "https://pt123.cdn.static123.com/images/thumbs/900x600/fit/2024/07/09/20231017164822-e942-wm_1720493626.jpg",
                "https://pt123.cdn.static123.com/images/thumbs/900x600/fit/2024/07/09/20231017164822-e942-wm_1720493626.jpg"
            ],
            "header": {
                "title": "CHO THUÊ NHÀ TRUNG TÂM THÀNH PHỐ LÀM VĂN PHÒNG",
                "address": "Địa chỉ: 278/35 Đường Tô Hiến Thành, Phường 15, Quận 10, Hồ Chí Minh",
                "attributes": {
                    "price": "23 triệu/tháng",
                    "acreage": "186.4m2",
                    "published": "11 giờ trước",
                    "hashtag": "659413"
                }
            },
            "mainContent": {
                "header": "Thông tin mô tả",
                "content": [
                    "Cho thuê nhà nguyên căn: 04 tầng x 186,4 m2, tại đường Tô Hiến Thành, gần siêu thị BigC Miền Đông",
                    "Địa chỉ: 278/35 Tô Hiến Thành, Phường 15, Quận 10, cạnh siêu thị BigC Miền Đông",
                    "Nhà rộng rãi, có điều hòa và máy nước nóng lạnh",
                    "Mặt hẻm xe hơi, nhà thoáng mát và có nhiều ánh sáng.",
                    "Ai có thiện chí thuê xin vui lòng liên hệ chị Thúy qua số điện thoại: 0943 782929",
                    "Trân trọng cảm ơn!"
                ]
            },
            "overview": {
                "header": "Đặc điểm tin đăng",
                "content": [
                    {
                        "name": "Mã tin:",
                        "content": "#659413"
                    },
                    {
                        "name": "Chuyên mục:",
                        "content": "Cho thuê mặt bằng Quận 10"
                    },
                    {
                        "name": "Khu vực",
                        "content": "Cho thuê mặt bằng Hồ Chí Minh"
                    },
                    {
                        "name": "Loại tin rao:",
                        "content": "Cho thuê mặt bằng"
                    },
                    {
                        "name": "Đối tượng thuê:",
                        "content": "Tất cả"
                    },
                    {
                        "name": "Gói tin:",
                        "content": "Tin miễn phí"
                    },
                    {
                        "name": "Ngày đăng:",
                        "content": "Thứ 3, 09:54 09/07/2024"
                    },
                    {
                        "name": "Ngày hết hạn:",
                        "content": "Chủ Nhật, 09:54 14/07/2024"
                    }
                ]
            },
            "contact": {
                "header": "Thông tin liên hệ",
                "content": [
                    {
                        "name": "Liên hệ:",
                        "content": "thi nguyễn"
                    },
                    {
                        "name": "Điện thoại:",
                        "content": "0962926001"
                    },
                    {
                        "name": "Zalo",
                        "content": "0962926001"
                    }
                ]
            }
        },
        {
            "images": [
                "https://pt123.cdn.static123.com/images/thumbs/900x600/fit/2024/07/08/img-9359_1720445048.jpg",
                "https://pt123.cdn.static123.com/images/thumbs/900x600/fit/2024/07/08/img-9352_1720445046.jpg",
                "https://pt123.cdn.static123.com/images/thumbs/900x600/fit/2024/07/08/img-9353_1720445046.jpg",
                "https://pt123.cdn.static123.com/images/thumbs/900x600/fit/2024/07/08/img-9355_1720445047.jpg",
                "https://pt123.cdn.static123.com/images/thumbs/900x600/fit/2024/07/08/img-9356_1720445047.jpg",
                "https://pt123.cdn.static123.com/images/thumbs/900x600/fit/2024/07/08/img-9354_1720445048.jpg",
                "https://pt123.cdn.static123.com/images/thumbs/900x600/fit/2024/07/08/img-9357_1720445048.jpg",
                "https://pt123.cdn.static123.com/images/thumbs/900x600/fit/2024/07/08/img-9358_1720445048.jpg",
                "https://pt123.cdn.static123.com/images/thumbs/900x600/fit/2024/07/08/img-9359_1720445048.jpg",
                "https://pt123.cdn.static123.com/images/thumbs/900x600/fit/2024/07/08/img-9352_1720445046.jpg"
            ],
            "header": {
                "title": "CHO THUÊ MẶT BẰNG KDC CITYLAND ĐƯỜNG NGUYỄN VĂN LƯỢNG",
                "address": "Địa chỉ: 255 Đường Nguyễn Văn Lượng, Phường 17, Quận Gò Vấp, Hồ Chí Minh",
                "attributes": {
                    "price": "18 triệu/tháng",
                    "acreage": "40m2",
                    "published": "1 ngày trước",
                    "hashtag": "659377"
                }
            },
            "mainContent": {
                "header": "Thông tin mô tả",
                "content": [
                    "Giá mềm Mặt bằng mặt tiền KDC CITYLAND Nguyễn Văn Lượng , P10, Q. Gò Vấp",
                    "- Diện tích: 40m2",
                    "- Kết cấu: Trệt suốt, riêng biệt",
                    "- Vị trí: Mặt tiền trục đường chính thuận lợi kinh doanh , dễ dàng nhận diện thương hiệu, Phù hợp kinh doanh nhiều ngành nghề",
                    "- Thời gian thuê: 2-5 năm",
                    "- Cọc & Thanh Toán: Thỏa Thuận.",
                    "- Thời gian bàn giao: Bàn Giao Ngay",
                    "Hotline : 0971021828",
                    "Zalo 0984230208 ( Làm Việc Chính Chủ ) Mr.Quân"
                ]
            },
            "overview": {
                "header": "Đặc điểm tin đăng",
                "content": [
                    {
                        "name": "Mã tin:",
                        "content": "#659377"
                    },
                    {
                        "name": "Chuyên mục:",
                        "content": "Cho thuê mặt bằng Quận Gò Vấp"
                    },
                    {
                        "name": "Khu vực",
                        "content": "Cho thuê mặt bằng Hồ Chí Minh"
                    },
                    {
                        "name": "Loại tin rao:",
                        "content": "Cho thuê mặt bằng"
                    },
                    {
                        "name": "Đối tượng thuê:",
                        "content": "Tất cả"
                    },
                    {
                        "name": "Gói tin:",
                        "content": "Tin miễn phí"
                    },
                    {
                        "name": "Ngày đăng:",
                        "content": "Thứ 2, 20:24 08/07/2024"
                    },
                    {
                        "name": "Ngày hết hạn:",
                        "content": "Thứ 7, 20:24 13/07/2024"
                    }
                ]
            },
            "contact": {
                "header": "Thông tin liên hệ",
                "content": [
                    {
                        "name": "Liên hệ:",
                        "content": "Quan"
                    },
                    {
                        "name": "Điện thoại:",
                        "content": "0971021828"
                    },
                    {
                        "name": "Zalo",
                        "content": "0971021828"
                    }
                ]
            }
        },
        {
            "images": [
                "https://pt123.cdn.static123.com/images/thumbs/900x600/fit/2024/07/08/1i283adqf-amb2re_1720430104.jpg",
                "https://pt123.cdn.static123.com/images/thumbs/900x600/fit/2024/07/08/1i283ae63-amb2re_1720430103.jpg",
                "https://pt123.cdn.static123.com/images/thumbs/900x600/fit/2024/07/08/1i283adv8-amb2re_1720430103.jpg",
                "https://pt123.cdn.static123.com/images/thumbs/900x600/fit/2024/07/08/1i283adqf-amb2re_1720430104.jpg"
            ],
            "header": {
                "title": "Mặt bằng kiốt cho thuê tại chợ linh xuân thủ đức",
                "address": "Địa chỉ: 61/14 Đường Quốc lộ 1K, Phường Linh Xuân, Thủ Đức, Hồ Chí Minh",
                "attributes": {
                    "price": "2.55 triệu/m2/tháng",
                    "acreage": "40m2",
                    "published": "1 ngày trước",
                    "hashtag": "659359"
                }
            },
            "mainContent": {
                "header": "Thông tin mô tả",
                "content": [
                    "Em hiện tại cho thuê mặt bằng tại chợ linh xuân ạ, ở trước nhà có sân để đậu xe trước nhà rộng thoái mát",
                    "ki ốt nằm trong lồng chợ ạ",
                    "trong tiệm có để lại máy lạnh cho khách thuê ki ốt sau sài ạ",
                    "ki ốt phù hợp làm kinh doanh kho dc hết ạ .",
                    "Mấy anh chị muốn thuê thì nhắn zalo e hoặc là điện trực tiếp coi nhà ạ ( điện nước xài nhiêu tính nhiêu theo nhà nước)",
                    "2tr500/1tháng ạ"
                ]
            },
            "overview": {
                "header": "Đặc điểm tin đăng",
                "content": [
                    {
                        "name": "Mã tin:",
                        "content": "#659359"
                    },
                    {
                        "name": "Chuyên mục:",
                        "content": "Cho thuê mặt bằng Thủ Đức"
                    },
                    {
                        "name": "Khu vực",
                        "content": "Cho thuê mặt bằng Hồ Chí Minh"
                    },
                    {
                        "name": "Loại tin rao:",
                        "content": "Cho thuê mặt bằng"
                    },
                    {
                        "name": "Đối tượng thuê:",
                        "content": "Nữ"
                    },
                    {
                        "name": "Gói tin:",
                        "content": "Tin miễn phí"
                    },
                    {
                        "name": "Ngày đăng:",
                        "content": "Thứ 2, 16:26 08/07/2024"
                    },
                    {
                        "name": "Ngày hết hạn:",
                        "content": "Thứ 7, 16:26 13/07/2024"
                    }
                ]
            },
            "contact": {
                "header": "Thông tin liên hệ",
                "content": [
                    {
                        "name": "Liên hệ:",
                        "content": "Thanh Trúc"
                    },
                    {
                        "name": "Điện thoại:",
                        "content": "0937526627"
                    },
                    {
                        "name": "Zalo",
                        "content": "0937526627"
                    }
                ]
            }
        },
        {
            "images": [
                "https://pt123.cdn.static123.com/images/thumbs/900x600/fit/2024/07/02/z5595826308622-05d5ab5be09936270b9dfb32b020e1f3_1719928606.jpg",
                "https://pt123.cdn.static123.com/images/thumbs/900x600/fit/2024/07/02/z5595827426153-62663f75ab8bcb20f0c017766d0a5cba_1719928599.jpg",
                "https://pt123.cdn.static123.com/images/thumbs/900x600/fit/2024/07/02/z5595827442325-506e2766dd0af2c235f653d787b76232_1719928599.jpg",
                "https://pt123.cdn.static123.com/images/thumbs/900x600/fit/2024/07/02/z5595826131722-9c9130d83b010b9f0901a607eb77a1c8_1719928602.jpg",
                "https://pt123.cdn.static123.com/images/thumbs/900x600/fit/2024/07/02/z5595826112312-8457ddf85040450a95bf5d7a45b91266_1719928602.jpg",
                "https://pt123.cdn.static123.com/images/thumbs/900x600/fit/2024/07/02/z5595826143256-dd5840289c52b7058b77377ae8acdcaf_1719928604.jpg",
                "https://pt123.cdn.static123.com/images/thumbs/900x600/fit/2024/07/02/z5595826308622-05d5ab5be09936270b9dfb32b020e1f3_1719928606.jpg",
                "https://pt123.cdn.static123.com/images/thumbs/900x600/fit/2024/07/02/z5595827426153-62663f75ab8bcb20f0c017766d0a5cba_1719928599.jpg"
            ],
            "header": {
                "title": "MẶT BẰNG GIÁ RẺ NẰM Ở MẶT TIỀN ĐƯỜNG LỚN TÂN SƠN, PHÒNG SẠCH SẼ CÓ TOLET RIÊNG",
                "address": "Địa chỉ: Đường Tân Sơn, Phường 15, Quận Tân Bình, Hồ Chí Minh",
                "attributes": {
                    "price": "6 triệu/tháng",
                    "acreage": "28m2",
                    "published": "1 ngày trước",
                    "hashtag": "278694"
                }
            },
            "mainContent": {
                "header": "Thông tin mô tả",
                "content": [
                    "Cho thuê mặt bằng giá rẻ phòng sạch sẽ tường ốp gạch men có to let riêng . Nằm trên mặt tiền đường lớn Tân sơn ( đường vào sân Golf Tân sơn nhất ). Thuận tiện cho việc kinh doanh buôn bán và văn phòng vv",
                    "Địa chỉ : 185 Tân sơn Phường 15 Tân bình TpHCM",
                    "Giá thuê : 6 Triệu / tháng",
                    "Liên hệ : 0973651544",
                    "0867003148",
                    "Gặp chú Huyên chủ nhà"
                ]
            },
            "overview": {
                "header": "Đặc điểm tin đăng",
                "content": [
                    {
                        "name": "Mã tin:",
                        "content": "#278694"
                    },
                    {
                        "name": "Chuyên mục:",
                        "content": "Cho thuê mặt bằng Quận Tân Bình"
                    },
                    {
                        "name": "Khu vực",
                        "content": "Cho thuê mặt bằng Hồ Chí Minh"
                    },
                    {
                        "name": "Loại tin rao:",
                        "content": "Cho thuê mặt bằng"
                    },
                    {
                        "name": "Đối tượng thuê:",
                        "content": "Tất cả"
                    },
                    {
                        "name": "Gói tin:",
                        "content": "Tin thường"
                    },
                    {
                        "name": "Ngày đăng:",
                        "content": "Thứ 2, 09:33 08/07/2024"
                    },
                    {
                        "name": "Ngày hết hạn:",
                        "content": "Thứ 7, 09:33 13/07/2024"
                    }
                ]
            },
            "contact": {
                "header": "Thông tin liên hệ",
                "content": [
                    {
                        "name": "Liên hệ:",
                        "content": "tranvanhuyen1404"
                    },
                    {
                        "name": "Điện thoại:",
                        "content": "0867003148"
                    },
                    {
                        "name": "Zalo",
                        "content": "0867003148"
                    }
                ]
            }
        },
        {
            "images": [
                "https://pt123.cdn.static123.com/images/thumbs/900x600/fit/2024/07/07/img-2628_1720339475.jpg",
                "https://pt123.cdn.static123.com/images/thumbs/900x600/fit/2024/07/07/img-2636_1720339470.jpg",
                "https://pt123.cdn.static123.com/images/thumbs/900x600/fit/2024/07/07/img-2635_1720339471.jpg",
                "https://pt123.cdn.static123.com/images/thumbs/900x600/fit/2024/07/07/img-2630_1720339472.jpg",
                "https://pt123.cdn.static123.com/images/thumbs/900x600/fit/2024/07/07/img-2628_1720339475.jpg"
            ],
            "header": {
                "title": "Cho thuê mặt bằng tại 186/11 Nguyễn Suý, Tân Quý, Tân Phú",
                "address": "Địa chỉ: 186/11 Đường Nguyễn Súy, Phường Tân Quý, Quận Tân Phú, Hồ Chí Minh",
                "attributes": {
                    "price": "6 triệu/tháng",
                    "acreage": "45m2",
                    "published": "2 ngày trước",
                    "hashtag": "659238"
                }
            },
            "mainContent": {
                "header": "Thông tin mô tả",
                "content": [
                    "Nhà cho thuê nguyên căn 186/11 Nguyễn Súy, P. Tân Quý, Q. Tân Phú (gần chợ Tân Hương, cách Aeon 1km).",
                    "3mx10m, 01 trệt + 01 gác lửng = 45m2, có máy nước nóng.",
                    "NHÀ THÍCH HỢP KINH DOANH ONLINE, HẺM RỘNG THOÁNG, AN NINH, GIAO HÀNG TIỆN LỢI.",
                    "Giá cho thuê 6.000.000 đồng/ tháng.",
                    "Đặt cọc 02 tháng. Miễn trung gian.",
                    "LH: Anh Long 0907523789/ Chị Trúc 0918.029.033"
                ]
            },
            "overview": {
                "header": "Đặc điểm tin đăng",
                "content": [
                    {
                        "name": "Mã tin:",
                        "content": "#659238"
                    },
                    {
                        "name": "Chuyên mục:",
                        "content": "Cho thuê mặt bằng Quận Tân Phú"
                    },
                    {
                        "name": "Khu vực",
                        "content": "Cho thuê mặt bằng Hồ Chí Minh"
                    },
                    {
                        "name": "Loại tin rao:",
                        "content": "Cho thuê mặt bằng"
                    },
                    {
                        "name": "Đối tượng thuê:",
                        "content": "Tất cả"
                    },
                    {
                        "name": "Gói tin:",
                        "content": "Tin miễn phí"
                    },
                    {
                        "name": "Ngày đăng:",
                        "content": "Chủ Nhật, 15:09 07/07/2024"
                    },
                    {
                        "name": "Ngày hết hạn:",
                        "content": "Thứ 6, 15:09 12/07/2024"
                    }
                ]
            },
            "contact": {
                "header": "Thông tin liên hệ",
                "content": [
                    {
                        "name": "Liên hệ:",
                        "content": "TRẦN TRÚC"
                    },
                    {
                        "name": "Điện thoại:",
                        "content": "0918029033"
                    },
                    {
                        "name": "Zalo",
                        "content": "0918029033"
                    }
                ]
            }
        },
        {
            "images": [
                "https://pt123.cdn.static123.com/images/thumbs/900x600/fit/2024/07/07/img-8217_1720323846.jpg",
                "https://pt123.cdn.static123.com/images/thumbs/900x600/fit/2024/07/07/img-8218_1720323846.jpg",
                "https://pt123.cdn.static123.com/images/thumbs/900x600/fit/2024/06/27/img-8064_1719495651.jpg",
                "https://pt123.cdn.static123.com/images/thumbs/900x600/fit/2024/06/27/1i1cttlnc-7rjk3a_1719495651.jpg",
                "https://pt123.cdn.static123.com/images/thumbs/900x600/fit/2024/07/07/img-8217_1720323846.jpg",
                "https://pt123.cdn.static123.com/images/thumbs/900x600/fit/2024/07/07/img-8218_1720323846.jpg"
            ],
            "header": {
                "title": "CHO THUÊ MẶT BẰNG 50m2 hẻm đường tân mỹ, quận 7",
                "address": "Địa chỉ: Đường Tân Mỹ, Phường Tân Thuận Tây, Quận 7, Hồ Chí Minh",
                "attributes": {
                    "price": "7 triệu/tháng",
                    "acreage": "50m2",
                    "published": "2 ngày trước",
                    "hashtag": "658411"
                }
            },
            "mainContent": {
                "header": "Thông tin mô tả",
                "content": [
                    "CHO THUÊ MẶT BẰNG 50m2 hẻm đường tân mỹ, quận 7",
                    "Mặt bằng hẻm 5x10m, điện nhà nước",
                    "Hẻm đông dân cư xe tải 2 tấn vô được",
                    "Phù hợp làm tiệm nail, spa, giặt sấy, bán đồ ăn",
                    "Giá: 7tr",
                    "LH: 0844244226"
                ]
            },
            "overview": {
                "header": "Đặc điểm tin đăng",
                "content": [
                    {
                        "name": "Mã tin:",
                        "content": "#658411"
                    },
                    {
                        "name": "Chuyên mục:",
                        "content": "Cho thuê mặt bằng Quận 7"
                    },
                    {
                        "name": "Khu vực",
                        "content": "Cho thuê mặt bằng Hồ Chí Minh"
                    },
                    {
                        "name": "Loại tin rao:",
                        "content": "Cho thuê mặt bằng"
                    },
                    {
                        "name": "Đối tượng thuê:",
                        "content": "Tất cả"
                    },
                    {
                        "name": "Gói tin:",
                        "content": "Tin thường"
                    },
                    {
                        "name": "Ngày đăng:",
                        "content": "Chủ Nhật, 10:44 07/07/2024"
                    },
                    {
                        "name": "Ngày hết hạn:",
                        "content": "Thứ 7, 20:39 27/07/2024"
                    }
                ]
            },
            "contact": {
                "header": "Thông tin liên hệ",
                "content": [
                    {
                        "name": "Liên hệ:",
                        "content": "Trần Ngọc Hoàng An"
                    },
                    {
                        "name": "Điện thoại:",
                        "content": "0844244226"
                    },
                    {
                        "name": "Zalo",
                        "content": "0844244226"
                    }
                ]
            }
        },
        {
            "images": [
                "https://pt123.cdn.static123.com/images/thumbs/900x600/fit/2023/07/10/eab63dfe-58bb-4e19-8707-1c34bc1254ca_1688977089.jpg",
                "https://pt123.cdn.static123.com/images/thumbs/900x600/fit/2023/07/10/8583373d-5f4a-47f1-a582-86de25386f8d_1688977086.jpg",
                "https://pt123.cdn.static123.com/images/thumbs/900x600/fit/2023/07/10/af05f7dc-5fa4-41da-9bb9-27bff62a7116_1688977086.jpg",
                "https://pt123.cdn.static123.com/images/thumbs/900x600/fit/2023/07/10/eab63dfe-58bb-4e19-8707-1c34bc1254ca_1688977089.jpg",
                "https://pt123.cdn.static123.com/images/thumbs/900x600/fit/2023/07/10/8583373d-5f4a-47f1-a582-86de25386f8d_1688977086.jpg"
            ],
            "header": {
                "title": "Cho thuê mặt bằng đường Nguyễn Thái Bình",
                "address": "Địa chỉ: 30 Đường Nguyễn Thái Bình, Phường 4, Quận Tân Bình, Hồ Chí Minh",
                "attributes": {
                    "price": "11 triệu/tháng",
                    "acreage": "40m2",
                    "published": "3 ngày trước",
                    "hashtag": "629940"
                }
            },
            "mainContent": {
                "header": "Thông tin mô tả",
                "content": [
                    "Cho Thuê Mặt Bằng đường Nguyễn Thái Bình. Tân Bình",
                    "Diện tích : 4x10m",
                    "Vị trí : Khu dân cư đông, sầm uất, thuận tiên đi lại, gần trường, siêu thị…",
                    "Phù hợp văn phòng, công ty… ( không kinh doanh ăn uống )",
                    "Đặt cọc 3 tháng.",
                    "Liên hệ chính chủ:",
                    "0907768585 anh Ân",
                    "0908409930 chị Thuỷ"
                ]
            },
            "overview": {
                "header": "Đặc điểm tin đăng",
                "content": [
                    {
                        "name": "Mã tin:",
                        "content": "#629940"
                    },
                    {
                        "name": "Chuyên mục:",
                        "content": "Cho thuê mặt bằng Quận Tân Bình"
                    },
                    {
                        "name": "Khu vực",
                        "content": "Cho thuê mặt bằng Hồ Chí Minh"
                    },
                    {
                        "name": "Loại tin rao:",
                        "content": "Cho thuê mặt bằng"
                    },
                    {
                        "name": "Đối tượng thuê:",
                        "content": "Tất cả"
                    },
                    {
                        "name": "Gói tin:",
                        "content": "Tin miễn phí"
                    },
                    {
                        "name": "Ngày đăng:",
                        "content": "Thứ 7, 17:08 06/07/2024"
                    },
                    {
                        "name": "Ngày hết hạn:",
                        "content": "Thứ 5, 17:08 11/07/2024"
                    }
                ]
            },
            "contact": {
                "header": "Thông tin liên hệ",
                "content": [
                    {
                        "name": "Liên hệ:",
                        "content": "Vân Trang"
                    },
                    {
                        "name": "Điện thoại:",
                        "content": "0906709500"
                    },
                    {
                        "name": "Zalo",
                        "content": "0906709500"
                    }
                ]
            }
        },
        {
            "images": [
                "https://pt123.cdn.static123.com/images/thumbs/900x600/fit/2024/07/06/20230708-090251_1720262725.jpg",
                "https://pt123.cdn.static123.com/images/thumbs/900x600/fit/2024/07/06/20230708-090231_1720262725.jpg",
                "https://pt123.cdn.static123.com/images/thumbs/900x600/fit/2024/07/06/20230708-090251_1720262725.jpg"
            ],
            "header": {
                "title": "Cho thuê mặt bằng kinh doanh - mặt tiện lộ xe tải ngang 9 mét - gần chợ",
                "address": "Địa chỉ: Thị trấn Lai Vung, Huyện Lai Vung, Đồng Tháp",
                "attributes": {
                    "price": "6 triệu/tháng",
                    "acreage": "180m2",
                    "published": "3 ngày trước",
                    "hashtag": "659151"
                }
            },
            "mainContent": {
                "header": "Thông tin mô tả",
                "content": [
                    "CHO THUÊ MẶT BẰNG - MẶT TIỀN NGANG 9 MÉT - LỘ XE TẢI",
                    "Diện tích = 180m2 = mặt tiền đường ngang 9 mét x dài 20 mét",
                    "Giá thuê = 6,000,000 đồng 1 tháng (thanh toán đầu mỗi tháng)",
                    "Cọc = 6,000,000 đồng (thanh toán ngay khi ký hợp đồng)",
                    "x GIÁ KHÔNG THƯƠNG LƯỢNG x",
                    "Địa chỉ mặt bằng: Số 274 - 276, Đường Vành Đai, Khóm 2, Thị trấn Lai Vung, Tỉnh Đồng Tháp",
                    "Hướng chính - ĐÔNG",
                    "Mặt bằng nằm ngay khu dân cư",
                    "Cách chợ Hòa Long 2 phút đi xe máy",
                    "Mặt bằng có 1 phòng ngủ (khung thép vách xi măng tấm) và 1 nhà vệ sinh tiện cho kinh doanh + lưu trú lại",
                    "LIÊN HỆ 0834.59.57.94 CHÍNH CHỦ"
                ]
            },
            "overview": {
                "header": "Đặc điểm tin đăng",
                "content": [
                    {
                        "name": "Mã tin:",
                        "content": "#659151"
                    },
                    {
                        "name": "Chuyên mục:",
                        "content": "Cho thuê mặt bằng Huyện Lai Vung"
                    },
                    {
                        "name": "Khu vực",
                        "content": "Cho thuê mặt bằng Đồng Tháp"
                    },
                    {
                        "name": "Loại tin rao:",
                        "content": "Cho thuê mặt bằng"
                    },
                    {
                        "name": "Đối tượng thuê:",
                        "content": "Tất cả"
                    },
                    {
                        "name": "Gói tin:",
                        "content": "Tin miễn phí"
                    },
                    {
                        "name": "Ngày đăng:",
                        "content": "Thứ 7, 14:28 06/07/2024"
                    },
                    {
                        "name": "Ngày hết hạn:",
                        "content": "Thứ 5, 14:28 11/07/2024"
                    }
                ]
            },
            "contact": {
                "header": "Thông tin liên hệ",
                "content": [
                    {
                        "name": "Liên hệ:",
                        "content": "Nguyễn Thị Mai Anh"
                    },
                    {
                        "name": "Điện thoại:",
                        "content": "0834595794"
                    },
                    {
                        "name": "Zalo",
                        "content": "0834595794"
                    }
                ]
            }
        },
        {
            "images": [],
            "header": {
                "title": "Cho thuê nhà cấp 4 - đậu được xe 7 chổ",
                "address": "Địa chỉ: Thành Phố Cao Lãnh, Đồng Tháp",
                "attributes": {
                    "price": "5 triệu/tháng",
                    "acreage": "88m2",
                    "published": "3 ngày trước",
                    "hashtag": "659150"
                }
            },
            "mainContent": {
                "header": "Thông tin mô tả",
                "content": [
                    "CHO THUÊ NHÀ CẤP 4 - MẶT TIỀN LỘ 2 LÀN XE TẢI - TRUNG TÂM PHƯỜNG 1 TP.CAO LÃNH - ĐẬU ĐƯỢC XE 7 CHỔ",
                    "Địa chỉ nhà cho thuê: Số 35, Đường Phạm Ngũ Lão, Phường 1, Thành phố Cao Lãnh, Tỉnh Đồng Tháp",
                    "Giá thuê: 5 triệu đồng 1 tháng (thanh toán đầu mỗi tháng) - GIÁ KHÔNG THƯƠNG LƯỢNG",
                    "Cọc: 5 triệu đồng (thanh toán ngay khi ký hợp đồng)",
                    "Tiền điện + tiền nước + tiền rác thải sinh hoạt,... bên thuê tự thanh toán với nhà cung cấp.",
                    "NHÀ TRỐNG",
                    "> có 1 phòng đậu/ đỗ được: 2 chiếc Honda Lead và 1 xe hơi 7 chổ (tổng cộng sức chứa 3 chiếc)",
                    "> có 1 phòng khách",
                    "> có 2 phòng ngủ (khung thép + vách xi măng tấm)",
                    "> có 1 nhà vệ sinh",
                    "> Cách công viên, bệnh viện, quán ăn,... 3 phút đi bằng xe máy",
                    "> Cách khu hành chánh công, bưu điện Tỉnh, ngân hàng, công an phường,... 5 phút đi xe máy",
                    "> Cách Co.opmart, Vincom, chợ,... 7 phút đi xe máy",
                    "> Nhà nằm trong khu dân cư đông đúc, yên tĩnh, an ninh",
                    "> Thích hợp định cư lâu dài và kinh doanh online",
                    "LIÊN HỆ 0834.59.57.94 CHÍNH CHỦ"
                ]
            },
            "overview": {
                "header": "Đặc điểm tin đăng",
                "content": [
                    {
                        "name": "Mã tin:",
                        "content": "#659150"
                    },
                    {
                        "name": "Chuyên mục:",
                        "content": "Cho thuê mặt bằng Thành Phố Cao Lãnh"
                    },
                    {
                        "name": "Khu vực",
                        "content": "Cho thuê mặt bằng Đồng Tháp"
                    },
                    {
                        "name": "Loại tin rao:",
                        "content": "Cho thuê mặt bằng"
                    },
                    {
                        "name": "Đối tượng thuê:",
                        "content": "Tất cả"
                    },
                    {
                        "name": "Gói tin:",
                        "content": "Tin miễn phí"
                    },
                    {
                        "name": "Ngày đăng:",
                        "content": "Thứ 7, 14:25 06/07/2024"
                    },
                    {
                        "name": "Ngày hết hạn:",
                        "content": "Thứ 5, 14:25 11/07/2024"
                    }
                ]
            },
            "contact": {
                "header": "Thông tin liên hệ",
                "content": [
                    {
                        "name": "Liên hệ:",
                        "content": "Nguyễn Thị Mai Anh"
                    },
                    {
                        "name": "Điện thoại:",
                        "content": "0834595794"
                    },
                    {
                        "name": "Zalo",
                        "content": "0834595794"
                    }
                ]
            }
        },
        {
            "images": [
                "https://pt123.cdn.static123.com/images/thumbs/900x600/fit/2024/07/06/mat-bang-cho-thue-gia-re-q7-tien-mo-van-phong-duong-so-10-ly-phuc-man-p-binh-thuan_1720245952.jpg",
                "https://pt123.cdn.static123.com/images/thumbs/900x600/fit/2024/07/06/mat-bang-cho-thue-gia-re-q7-tien-mo-van-phong-duong-so-10-ly-phuc-man-p-binh-thuan-2_1720245949.jpg",
                "https://pt123.cdn.static123.com/images/thumbs/900x600/fit/2024/07/06/mat-bang-cho-thue-gia-re-q7-tien-mo-van-phong-duong-so-10-ly-phuc-man-p-binh-thuan-4_1720245949.jpg",
                "https://pt123.cdn.static123.com/images/thumbs/900x600/fit/2024/07/06/mat-bang-cho-thue-gia-re-q7-tien-mo-van-phong-duong-so-10-ly-phuc-man-p-binh-thuan_1720245952.jpg",
                "https://pt123.cdn.static123.com/images/thumbs/900x600/fit/2024/07/06/mat-bang-cho-thue-gia-re-q7-tien-mo-van-phong-duong-so-10-ly-phuc-man-p-binh-thuan-2_1720245949.jpg"
            ],
            "header": {
                "title": "Mặt bằng cho thuê văn phòng vừa và nhỏ Quận 7- Giá tốt - 10 triệu/tháng",
                "address": "Địa chỉ: Đường số 10, Phường Bình Thuận, Quận 7, Hồ Chí Minh",
                "attributes": {
                    "price": "10 triệu/tháng",
                    "acreage": "42m2",
                    "published": "3 ngày trước",
                    "hashtag": "659135"
                }
            },
            "mainContent": {
                "header": "Thông tin mô tả",
                "content": [
                    "++Thông tin mặt bằng:",
                    "- Địa chỉ: 22A đường số 10, P.Bình Thuận, Q7. Tp.Hcm.",
                    "- Diện tích: 42 m2 (4.5 x 8), sân 1.5m.",
                    "- Mặt bằng chính chủ hướng tốt Tây Nam, có sân để xe, vỉa hè rộng, không gian thoáng mát, khu vực an ninh tốt. Mặt bằng có sẵn các tiện ích cơ bản điện, nước, internet.",
                    "- Gần các trường cấp 2, 3, chợ, siêu thị tiện tích, nhà thuốc, nơi tập trung nhiều công nhân,sinh viên.",
                    "- Vị trí thuận lợi: Dễ dàng di chuyển đến các khu vực lân cận.",
                    "- Mặt bằng có thể tùy chỉnh theo ý muốn, phù hợp cho công ty vừa và nhỏ thích hợp làm văn phòng.",
                    "- Mức giá thuê tốt, hợp lý: 10 triệu/tháng.",
                    "++Liên hệ để biết thêm thông tin:",
                    "Điện thoại: 0937.922.265 (Chú Thao) Chính chủ"
                ]
            },
            "overview": {
                "header": "Đặc điểm tin đăng",
                "content": [
                    {
                        "name": "Mã tin:",
                        "content": "#659135"
                    },
                    {
                        "name": "Chuyên mục:",
                        "content": "Cho thuê mặt bằng Quận 7"
                    },
                    {
                        "name": "Khu vực",
                        "content": "Cho thuê mặt bằng Hồ Chí Minh"
                    },
                    {
                        "name": "Loại tin rao:",
                        "content": "Cho thuê mặt bằng"
                    },
                    {
                        "name": "Đối tượng thuê:",
                        "content": "Tất cả"
                    },
                    {
                        "name": "Gói tin:",
                        "content": "Tin miễn phí"
                    },
                    {
                        "name": "Ngày đăng:",
                        "content": "Thứ 7, 13:06 06/07/2024"
                    },
                    {
                        "name": "Ngày hết hạn:",
                        "content": "Thứ 5, 13:06 11/07/2024"
                    }
                ]
            },
            "contact": {
                "header": "Thông tin liên hệ",
                "content": [
                    {
                        "name": "Liên hệ:",
                        "content": "Kiss Mh"
                    },
                    {
                        "name": "Điện thoại:",
                        "content": "0938727860"
                    },
                    {
                        "name": "Zalo",
                        "content": "0938727860"
                    }
                ]
            }
        },
        {
            "images": [
                "https://pt123.cdn.static123.com/images/thumbs/900x600/fit/2024/07/05/9bb4d496da9721c97886_1720171511.jpg",
                "https://pt123.cdn.static123.com/images/thumbs/900x600/fit/2024/07/05/000-11b1aad39bd2608c39c3_1720171511.jpg",
                "https://pt123.cdn.static123.com/images/thumbs/900x600/fit/2024/07/05/6c67c7ebc9ea32b46bfb_1720171511.jpg",
                "https://pt123.cdn.static123.com/images/thumbs/900x600/fit/2024/07/05/8e78d1ecdeed25b37cfc_1720171511.jpg",
                "https://pt123.cdn.static123.com/images/thumbs/900x600/fit/2024/07/05/9bb4d496da9721c97886_1720171511.jpg",
                "https://pt123.cdn.static123.com/images/thumbs/900x600/fit/2024/07/05/000-11b1aad39bd2608c39c3_1720171511.jpg"
            ],
            "header": {
                "title": "Cho Thuê Tòa Nhà Góc 2 mặt tiền Khu Vũ Tông Phan An Phú Quận 2 hầm 5 Tầng nổi 1500m²",
                "address": "Địa chỉ: Phố Vũ Tông Phan, Phường An Phú, Quận 2, Hồ Chí Minh",
                "attributes": {
                    "price": "330 triệu/tháng",
                    "acreage": "1000m2",
                    "published": "4 ngày trước",
                    "hashtag": "659081"
                }
            },
            "mainContent": {
                "header": "Thông tin mô tả",
                "content": [
                    "Cho Thuê Tòa Nhà Góc 2 mặt tiền Đường Lương định của An Phú Quận 2 hầm 5 Tầng nổi 1500m²-",
                    "Gía Thuê: 330tr/tháng ",
                    "Diện Tích: 15x20m",
                    "Xây Dựng : hầm 5 Tầng nổi, tổng diện tích 1500m2 sàn thang máy tốc độ cao, điều hòa trung tâm, căn góc 2 mặt tiền, vị trí đắc địa...",
                    "Nhà mới với thiết kế sang trọng, hiện đại phù hợp kinh doanh Spa, Văn phòng, Studio, Showroom,...",
                    "Giỏ Hàng đa dạng sản phẩm - Gía Tốt",
                    "Vui lòng Liên hệ : 0901 302 123 (Luân Nguyễn) để được hỗ trợ thêm thông tin & xem Nhà trực tiếp"
                ]
            },
            "overview": {
                "header": "Đặc điểm tin đăng",
                "content": [
                    {
                        "name": "Mã tin:",
                        "content": "#659081"
                    },
                    {
                        "name": "Chuyên mục:",
                        "content": "Cho thuê mặt bằng Quận 2"
                    },
                    {
                        "name": "Khu vực",
                        "content": "Cho thuê mặt bằng Hồ Chí Minh"
                    },
                    {
                        "name": "Loại tin rao:",
                        "content": "Cho thuê mặt bằng"
                    },
                    {
                        "name": "Đối tượng thuê:",
                        "content": "Tất cả"
                    },
                    {
                        "name": "Gói tin:",
                        "content": "Tin miễn phí"
                    },
                    {
                        "name": "Ngày đăng:",
                        "content": "Thứ 6, 16:26 05/07/2024"
                    },
                    {
                        "name": "Ngày hết hạn:",
                        "content": "Thứ 4, 16:26 10/07/2024"
                    }
                ]
            },
            "contact": {
                "header": "Thông tin liên hệ",
                "content": [
                    {
                        "name": "Liên hệ:",
                        "content": "nguyễn văn luân"
                    },
                    {
                        "name": "Điện thoại:",
                        "content": "0901302123"
                    },
                    {
                        "name": "Zalo",
                        "content": "0901302123"
                    }
                ]
            }
        },
        {
            "images": [
                "https://pt123.cdn.static123.com/images/thumbs/900x600/fit/2024/07/05/z3681121847357-c3fc049923ed2dda7e2302539f794c30_1720171289.jpg",
                "https://pt123.cdn.static123.com/images/thumbs/900x600/fit/2024/07/05/z02818388271595-c02c2adf428e0347cdf9667648e44d6e_1720171286.jpg",
                "https://pt123.cdn.static123.com/images/thumbs/900x600/fit/2024/07/05/z3353734127819-1d6f0216dfa6043b1089752549b3c0ba_1720171286.jpg",
                "https://pt123.cdn.static123.com/images/thumbs/900x600/fit/2024/07/05/z3353734155039-aa8992b1b127b29c601f0954a71973c3_1720171287.jpg",
                "https://pt123.cdn.static123.com/images/thumbs/900x600/fit/2024/07/05/z3353734199613-e0930b952523fbe4e2991ad9b72c0407_1720171288.jpg",
                "https://pt123.cdn.static123.com/images/thumbs/900x600/fit/2024/07/05/z3681121847357-c3fc049923ed2dda7e2302539f794c30_1720171289.jpg",
                "https://pt123.cdn.static123.com/images/thumbs/900x600/fit/2024/07/05/z02818388271595-c02c2adf428e0347cdf9667648e44d6e_1720171286.jpg"
            ],
            "header": {
                "title": "Cho thuê Building 2 mặt tiền Đường Trung Tâm Quận 2, Hầm 7, sàn 1100m²",
                "address": "Địa chỉ: Đường Tạ Hiện, Phường Thạnh Mỹ Lợi, Quận 2, Hồ Chí Minh",
                "attributes": {
                    "price": "130 triệu/tháng",
                    "acreage": "1000m2",
                    "published": "4 ngày trước",
                    "hashtag": "659080"
                }
            },
            "mainContent": {
                "header": "Thông tin mô tả",
                "content": [
                    "Cho thuê Building 2 mặt tiền Hầm 7 sàn 1100m² Đường Trung Tâm Quận 2",
                    "Diện Tích: 10x20m",
                    "Xây Dựng : Tòa nhà 8 tầng hai mặt tiền ( Hầm 7 lầu sàn trống suốt), thiết kế văn phòng, đầy đủ máy lạnh, thang máy, PCCC, Hệ Thống Camera giám sát, nhà mới 100%",
                    "Gía Thuê: 130 tr/tháng .",
                    "Vui lòng Liên hệ :0901 302 123 để được hỗ trợ thêm thông tin & xem Nhà trực tiếp"
                ]
            },
            "overview": {
                "header": "Đặc điểm tin đăng",
                "content": [
                    {
                        "name": "Mã tin:",
                        "content": "#659080"
                    },
                    {
                        "name": "Chuyên mục:",
                        "content": "Cho thuê mặt bằng Quận 2"
                    },
                    {
                        "name": "Khu vực",
                        "content": "Cho thuê mặt bằng Hồ Chí Minh"
                    },
                    {
                        "name": "Loại tin rao:",
                        "content": "Cho thuê mặt bằng"
                    },
                    {
                        "name": "Đối tượng thuê:",
                        "content": "Tất cả"
                    },
                    {
                        "name": "Gói tin:",
                        "content": "Tin miễn phí"
                    },
                    {
                        "name": "Ngày đăng:",
                        "content": "Thứ 6, 16:21 05/07/2024"
                    },
                    {
                        "name": "Ngày hết hạn:",
                        "content": "Thứ 4, 16:21 10/07/2024"
                    }
                ]
            },
            "contact": {
                "header": "Thông tin liên hệ",
                "content": [
                    {
                        "name": "Liên hệ:",
                        "content": "nguyễn văn luân"
                    },
                    {
                        "name": "Điện thoại:",
                        "content": "0901302123"
                    },
                    {
                        "name": "Zalo",
                        "content": "0901302123"
                    }
                ]
            }
        },
        {
            "images": [
                "https://pt123.cdn.static123.com/images/thumbs/900x600/fit/2024/07/05/z5301647899294-ad0ff5e2dfbc19c9ed13681cd4695496_1720171179.jpg",
                "https://pt123.cdn.static123.com/images/thumbs/900x600/fit/2024/07/05/cho-thue-nha-mat-tien-quan-2-169267554014410_1720171173.jpg",
                "https://pt123.cdn.static123.com/images/thumbs/900x600/fit/2024/07/05/z5301647698061-f3eebe1de6487662f85246ba7b00cc25_1720171173.jpg",
                "https://pt123.cdn.static123.com/images/thumbs/900x600/fit/2024/07/05/z5301647714704-4ca99d6ae616949c75439e08c2dd7e1e_1720171175.jpg",
                "https://pt123.cdn.static123.com/images/thumbs/900x600/fit/2024/07/05/z5301647778968-fc0096cbe0a28e8403ced4c1fec76d30_1720171177.jpg",
                "https://pt123.cdn.static123.com/images/thumbs/900x600/fit/2024/07/05/z5301647842261-cde94289a309f938ba03142da4c25024_1720171177.jpg",
                "https://pt123.cdn.static123.com/images/thumbs/900x600/fit/2024/07/05/z5301647899294-ad0ff5e2dfbc19c9ed13681cd4695496_1720171179.jpg",
                "https://pt123.cdn.static123.com/images/thumbs/900x600/fit/2024/07/05/cho-thue-nha-mat-tien-quan-2-169267554014410_1720171173.jpg"
            ],
            "header": {
                "title": "Cho Thuê Tòa nhà văn phòng Đường Lương định của P. An Phú Hầm 5 sàn trống, Quận 2",
                "address": "Địa chỉ: Phố Lương Định Của, Phường An Phú, Quận 2, Hồ Chí Minh",
                "attributes": {
                    "price": "90 triệu/tháng",
                    "acreage": "600m2",
                    "published": "4 ngày trước",
                    "hashtag": "659079"
                }
            },
            "mainContent": {
                "header": "Thông tin mô tả",
                "content": [
                    "Cho thuê Tòa nhà văn phòng Hầm 5 sàn trống Đường Lương định của An Phú Quận 2",
                    "Mô Tả Sản Phẩm ",
                    "Diện Tích: 7x20m",
                    "Xây Dựng : Hầm 5 sàn trống suốt Thiết kế văn phòng, thang máy, máy lạnh đầy đủ, vị trí đắc địa ngay mặt tiền lương định của",
                    "Gía Thuê: 90 tr/tháng .",
                    "Nhà mới với thiết kế sang trọng, hiện đại phù hợp kinh doanh Spa, Văn phòng, Studio, Showroom,...",
                    "Giỏ Hàng Phong Phú Và Giá Tốt - Tư Vấn Hỗ Trợ Nhiệt Tình",
                    "Vui lòng Liên hệ :0901 302 123 để được hỗ trợ thêm thông tin & xem Nhà trực tiếp"
                ]
            },
            "overview": {
                "header": "Đặc điểm tin đăng",
                "content": [
                    {
                        "name": "Mã tin:",
                        "content": "#659079"
                    },
                    {
                        "name": "Chuyên mục:",
                        "content": "Cho thuê mặt bằng Quận 2"
                    },
                    {
                        "name": "Khu vực",
                        "content": "Cho thuê mặt bằng Hồ Chí Minh"
                    },
                    {
                        "name": "Loại tin rao:",
                        "content": "Cho thuê mặt bằng"
                    },
                    {
                        "name": "Đối tượng thuê:",
                        "content": "Tất cả"
                    },
                    {
                        "name": "Gói tin:",
                        "content": "Tin miễn phí"
                    },
                    {
                        "name": "Ngày đăng:",
                        "content": "Thứ 6, 16:19 05/07/2024"
                    },
                    {
                        "name": "Ngày hết hạn:",
                        "content": "Thứ 4, 16:19 10/07/2024"
                    }
                ]
            },
            "contact": {
                "header": "Thông tin liên hệ",
                "content": [
                    {
                        "name": "Liên hệ:",
                        "content": "nguyễn văn luân"
                    },
                    {
                        "name": "Điện thoại:",
                        "content": "0901302123"
                    },
                    {
                        "name": "Zalo",
                        "content": "0901302123"
                    }
                ]
            }
        },
        {
            "images": [
                "https://pt123.cdn.static123.com/images/thumbs/900x600/fit/2024/07/05/000-540956512921-5ef8314a8a9c53dfac93d342dd0d4aef_1720170995.jpg",
                "https://pt123.cdn.static123.com/images/thumbs/900x600/fit/2024/07/05/000-540956512921-5ef8314a8a9c53dfac93d342dd0d4aef_1720170995.jpg",
                "https://pt123.cdn.static123.com/images/thumbs/900x600/fit/2024/07/05/000-540956512921-5ef8314a8a9c53dfac93d342dd0d4aef_1720170995.jpg"
            ],
            "header": {
                "title": "Cho thuê Tòa nhà văn phòng Đường Trần Lựu, An Phú, Quận 2. Hầm 5 tầng nổi 500m²",
                "address": "Địa chỉ: Trần Lưu, Phường An Phú, Quận 2, Hồ Chí Minh",
                "attributes": {
                    "price": "70 triệu/tháng",
                    "acreage": "500m2",
                    "published": "4 ngày trước",
                    "hashtag": "659078"
                }
            },
            "mainContent": {
                "header": "Thông tin mô tả",
                "content": [
                    "Cho thuê Tòa nhà văn phòng Đường Trần Lựu, An Phú, Quận 2. Hầm 5 tầng nổi 500m²",
                    "Thông Tin Sản Phẩm ",
                    "DIỆN TÍCH: 5x20m",
                    "KẾT CẤU: Hầm 5 tâng nổi Vách dựng kính full mặt tiền, thiết kế sàn trống suốt, thang máy cuối nhà Tối ưu diện tích và không gian sử dụng , trang bị đầy đủ máy lạnh nhà mới 100%",
                    "GIÁ THUÊ: 70 tr/tháng",
                    "VỊ TRÍ : Vị trí đắc địa ngay trục đường chính phù hợp làm văn phòng, showroom, spa kết hợp ở",
                    "Giỏ Hàng đa dạng sản phẩm – Gía tốt",
                    "️ Vui Lòng Liên hệ : Luân Nguyễn (có zalo) để được xem nhà và nhiều sản phẩm khác"
                ]
            },
            "overview": {
                "header": "Đặc điểm tin đăng",
                "content": [
                    {
                        "name": "Mã tin:",
                        "content": "#659078"
                    },
                    {
                        "name": "Chuyên mục:",
                        "content": "Cho thuê mặt bằng Quận 2"
                    },
                    {
                        "name": "Khu vực",
                        "content": "Cho thuê mặt bằng Hồ Chí Minh"
                    },
                    {
                        "name": "Loại tin rao:",
                        "content": "Cho thuê mặt bằng"
                    },
                    {
                        "name": "Đối tượng thuê:",
                        "content": "Tất cả"
                    },
                    {
                        "name": "Gói tin:",
                        "content": "Tin miễn phí"
                    },
                    {
                        "name": "Ngày đăng:",
                        "content": "Thứ 6, 16:17 05/07/2024"
                    },
                    {
                        "name": "Ngày hết hạn:",
                        "content": "Thứ 4, 16:17 10/07/2024"
                    }
                ]
            },
            "contact": {
                "header": "Thông tin liên hệ",
                "content": [
                    {
                        "name": "Liên hệ:",
                        "content": "nguyễn văn luân"
                    },
                    {
                        "name": "Điện thoại:",
                        "content": "0901302123"
                    },
                    {
                        "name": "Zalo",
                        "content": "0901302123"
                    }
                ]
            }
        }
    ]
}